src/__init__.py
src/ARCA/ARCA.py
src/ARCA/__init__.py
src/ARCA/Cartas de porte electronicas/AplicativoCartasDePorteElectronicas.py
src/ARCA/Cartas de porte electronicas/__init__.py
src/Chrome/Chrome.py
src/Chrome/__init__.py
src/Excel/Excel.py
src/Excel/__init__.py
src/Terminal/Terminal.py
src/Terminal/__init__.py
src/Windows/Windows.py
src/Windows/__init__.py
tests/__init__.py
glgrpa-0.1.dist-info/METADATA
glgrpa-0.1.dist-info/WHEEL
glgrpa-0.1.dist-info/top_level.txt
glgrpa-0.1.dist-info/RECORD
