Metadata-Version: 2.2
Name: glgrpa
Version: 0.1
Summary: Librería para automatización de tareas en RPA dentro de Grupo Los Grobo
Home-page: https://GrupoLosGrobo@dev.azure.com/GrupoLosGrobo/GrupoLosGrobo%20RPA/_git/GrupoLosGrobo%20RPA
Author: Bellome, Gabriel <gabriel.bellome@losgrobo.com>
Author-email: gabriel.bellome@losgrobo.com
Classifier: Programming Language :: Python :: 3
Classifier: License :: OSI Approved :: MIT License
Classifier: Operating System :: OS Independent
Requires-Python: >=3.6
Requires-Dist: selenium
Requires-Dist: pandas
Dynamic: author
Dynamic: author-email
Dynamic: classifier
Dynamic: description
Dynamic: description-content-type
Dynamic: home-page
Dynamic: requires-dist
Dynamic: requires-python
Dynamic: summary
